[
  {
    "inp": 0,
    "out": 75
  },
  {
    "inp": 1,
    "out": 40
  },
  {
    "inp": 2,
    "out": 51
  },
  {
    "inp": 3,
    "out": 53
  },
  {
    "inp": 4,
    "out": 17
  },
  {
    "inp": 5,
    "out": 21
  },
  {
    "inp": 10,
    "out": 20
  },
  {
    "inp": 13,
    "out": 7
  },
  {
    "inp": 14,
    "out": 33
  },
  {
    "inp": 15,
    "out": 67
  },
  {
    "inp": 16,
    "out": 82
  },
  {
    "inp": 18,
    "out": 80
  },
  {
    "inp": 23,
    "out": 46
  },
  {
    "inp": 27,
    "out": 76
  },
  {
    "inp": 28,
    "out": 12
  },
  {
    "inp": 31,
    "out": 36
  },
  {
    "inp": 35,
    "out": 24
  },
  {
    "inp": 37,
    "out": 6
  },
  {
    "inp": 39,
    "out": 38
  },
  {
    "inp": 41,
    "out": 92
  },
  {
    "inp": 42,
    "out": 55
  },
  {
    "inp": 43,
    "out": 34
  },
  {
    "inp": 44,
    "out": 83
  },
  {
    "inp": 45,
    "out": 19
  },
  {
    "inp": 48,
    "out": 9
  },
  {
    "inp": 49,
    "out": 72
  },
  {
    "inp": 50,
    "out": 57
  },
  {
    "inp": 56,
    "out": 30
  },
  {
    "inp": 58,
    "out": 78
  },
  {
    "inp": 59,
    "out": 52
  },
  {
    "inp": 60,
    "out": 93
  },
  {
    "inp": 61,
    "out": 66
  },
  {
    "inp": 62,
    "out": 79
  },
  {
    "inp": 64,
    "out": 70
  },
  {
    "inp": 65,
    "out": 22
  },
  {
    "inp": 68,
    "out": 47
  },
  {
    "inp": 69,
    "out": 89
  },
  {
    "inp": 73,
    "out": 11
  },
  {
    "inp": 74,
    "out": 90
  },
  {
    "inp": 77,
    "out": 32
  },
  {
    "inp": 81,
    "out": 8
  },
  {
    "inp": 84,
    "out": 63
  },
  {
    "inp": 86,
    "out": 25
  },
  {
    "inp": 87,
    "out": 71
  },
  {
    "inp": 88,
    "out": 54
  },
  {
    "inp": 91,
    "out": 29
  },
  {
    "inp": 94,
    "out": 96
  },
  {
    "inp": 95,
    "out": 26
  }
]